vibe/__init__.py
vibe/style.py
streamlit_vibe-0.2.2.dist-info/METADATA
streamlit_vibe-0.2.2.dist-info/WHEEL
streamlit_vibe-0.2.2.dist-info/licenses/LICENSE
streamlit_vibe-0.2.2.dist-info/RECORD
