Metadata-Version: 2.4
Name: streamlit-vibe
Version: 0.2.2
Summary: Add your description here
Author-email: Alejandro Piad <apiad@apiad.net>
License-File: LICENSE
Requires-Python: >=3.12
Requires-Dist: streamlit>=1.52.2
